survival_analysis/__init__.py
survival_analysis/utils.py
survival_analysis/api/__init__.py
survival_analysis/api/api.py
survival_analysis/database_preparation/__init__.py
survival_analysis/database_preparation/schema.py
survival_analysis/database_preparation/sql_interactions.py
survival_analysis/logger/__init__.py
survival_analysis/logger/logger.py
survival_analysis/model_preparation/__init__.py
survival_analysis/model_preparation/model_AFT.py
survival_analysis-0.0.3.dist-info/LICENSE
survival_analysis-0.0.3.dist-info/METADATA
survival_analysis-0.0.3.dist-info/WHEEL
survival_analysis-0.0.3.dist-info/top_level.txt
survival_analysis-0.0.3.dist-info/RECORD
