Metadata-Version: 2.1
Name: survival-analysis
Version: 0.0.3
Summary: Survival Analysis: Customer Churn and CLV Prediction
Home-page: UNKNOWN
Author: Anna Manasyan, Anna Shaljyan, Ela Khachatryan, Sergey Tovmasyan
License: UNKNOWN
Platform: UNKNOWN
License-File: LICENSE
Requires-Dist: annotated-types ==0.6.0
Requires-Dist: anyio ==3.7.1
Requires-Dist: appnope ==0.1.3
Requires-Dist: astor ==0.8.1
Requires-Dist: asttokens ==2.4.1
Requires-Dist: autograd ==1.6.2
Requires-Dist: autograd-gamma ==0.5.0
Requires-Dist: click ==8.1.7
Requires-Dist: comm ==0.2.0
Requires-Dist: contourpy ==1.2.0
Requires-Dist: cycler ==0.12.1
Requires-Dist: DateTime ==5.3
Requires-Dist: debugpy ==1.8.0
Requires-Dist: decorator ==5.1.1
Requires-Dist: executing ==2.0.1
Requires-Dist: fastapi ==0.105.0
Requires-Dist: fonttools ==4.46.0
Requires-Dist: formulaic ==0.6.6
Requires-Dist: future ==0.18.3
Requires-Dist: h11 ==0.14.0
Requires-Dist: idna ==3.6
Requires-Dist: interface-meta ==1.3.0
Requires-Dist: ipykernel ==6.27.1
Requires-Dist: ipython ==8.18.1
Requires-Dist: jedi ==0.19.1
Requires-Dist: jupyter-client ==8.6.0
Requires-Dist: jupyter-core ==5.5.0
Requires-Dist: kiwisolver ==1.4.5
Requires-Dist: lifelines ==0.27.8
Requires-Dist: matplotlib ==3.8.2
Requires-Dist: matplotlib-inline ==0.1.6
Requires-Dist: nest-asyncio ==1.5.8
Requires-Dist: numpy ==1.26.2
Requires-Dist: packaging ==23.2
Requires-Dist: pandas ==2.1.4
Requires-Dist: parso ==0.8.3
Requires-Dist: pexpect ==4.9.0
Requires-Dist: Pillow ==10.1.0
Requires-Dist: platformdirs ==4.1.0
Requires-Dist: prompt-toolkit ==3.0.43
Requires-Dist: psutil ==5.9.6
Requires-Dist: ptyprocess ==0.7.0
Requires-Dist: pure-eval ==0.2.2
Requires-Dist: pydantic ==2.5.2
Requires-Dist: pydantic-core ==2.14.5
Requires-Dist: Pygments ==2.17.2
Requires-Dist: pyparsing ==3.1.1
Requires-Dist: python-dateutil ==2.8.2
Requires-Dist: python-multipart ==0.0.6
Requires-Dist: pytz ==2023.3.post1
Requires-Dist: pyzmq ==25.1.2
Requires-Dist: scipy ==1.11.4
Requires-Dist: six ==1.16.0
Requires-Dist: sniffio ==1.3.0
Requires-Dist: SQLAlchemy ==2.0.23
Requires-Dist: stack-data ==0.6.3
Requires-Dist: starlette ==0.27.0
Requires-Dist: tornado ==6.4
Requires-Dist: traitlets ==5.14.0
Requires-Dist: typing ==3.7.4.3
Requires-Dist: typing-extensions ==4.9.0
Requires-Dist: tzdata ==2023.3
Requires-Dist: uvicorn ==0.24.0.post1
Requires-Dist: wcwidth ==0.2.12
Requires-Dist: wrapt ==1.16.0
Requires-Dist: zope.interface ==6.1
